libpypsg/__init__.py
libpypsg/docker.py
libpypsg/exceptions.py
libpypsg/request.py
libpypsg/settings.py
libpypsg/units.py
libpypsg/cfg/__init__.py
libpypsg/cfg/base.py
libpypsg/cfg/config.py
libpypsg/cfg/models.py
libpypsg/globes/__init__.py
libpypsg/globes/decoder.py
libpypsg/globes/globes.py
libpypsg/globes/molec.json
libpypsg/globes/structure.py
libpypsg/globes/exocam/__init__.py
libpypsg/globes/exocam/exocam.py
libpypsg/globes/exoplasim/__init__.py
libpypsg/globes/exoplasim/exoplasim.py
libpypsg/globes/waccm/__init__.py
libpypsg/globes/waccm/waccm.py
libpypsg/lyr/__init__.py
libpypsg/lyr/lyr.py
libpypsg/rad/__init__.py
libpypsg/rad/rad.py
libpypsg/trn/__init__.py
libpypsg/trn/trn.py
libpypsg-0.5.0.dist-info/licenses/LICENSE
libpypsg-0.5.0.dist-info/METADATA
libpypsg-0.5.0.dist-info/WHEEL
libpypsg-0.5.0.dist-info/top_level.txt
libpypsg-0.5.0.dist-info/RECORD
