Metadata-Version: 2.4
Name: libpypsg
Version: 0.5.0
Summary: A Python library for accessing the Planetary System Generator.
Author-email: Ted Johnson <ted.johnson@unlv.edu>
Maintainer-email: Ted Johnson <ted.johnson@unlv.edu>
License: MIT License
Project-URL: Repository, https://github.com/tedjohnson12/libpypsg
Project-URL: Issues, https://github.com/tedjohnson12/libpypsg/issues
Keywords: astronomy,exoplanet,planet,spectroscopy,PSG
Classifier: Development Status :: 4 - Beta
Classifier: Intended Audience :: Science/Research
Classifier: Topic :: Scientific/Engineering :: Astronomy
Classifier: License :: OSI Approved :: MIT License
Classifier: Programming Language :: Python :: 3
Classifier: Programming Language :: Python :: 3.10
Classifier: Programming Language :: Python :: 3.11
Classifier: Programming Language :: Python :: 3.12
Classifier: Programming Language :: Python :: 3.13
Classifier: Operating System :: OS Independent
Requires-Python: >=3.10
License-File: LICENSE
Requires-Dist: astropy
Requires-Dist: numpy
Requires-Dist: requests
Requires-Dist: python-dateutil
Requires-Dist: netCDF4
Provides-Extra: dev
Requires-Dist: cartopy; extra == "dev"
Requires-Dist: matplotlib; extra == "dev"
Requires-Dist: pytest; extra == "dev"
Requires-Dist: pep8; extra == "dev"
Requires-Dist: pydata-sphinx-theme; extra == "dev"
Requires-Dist: numpydoc; extra == "dev"
Requires-Dist: sphinx; extra == "dev"
Requires-Dist: sphinx-automodapi; extra == "dev"
Requires-Dist: sphinx-gallery; extra == "dev"
Requires-Dist: sphinxcontrib-bibtex; extra == "dev"
Requires-Dist: sphinxcontrib-napoleon; extra == "dev"
Requires-Dist: sphinxcontrib-bibtex; extra == "dev"
Dynamic: license-file
